symao/__init__.py
symao/_version.py
symao/propagation.py
symao/turbolence.py
symao/zernike.py
symao-1.0.2.dist-info/licenses/LICENSE
symao-1.0.2.dist-info/METADATA
symao-1.0.2.dist-info/WHEEL
symao-1.0.2.dist-info/top_level.txt
symao-1.0.2.dist-info/RECORD
