Metadata-Version: 2.4
Name: symao
Version: 1.0.2
Summary: A collection of Sympy expressions used in Adaptive Optics
Author-email: Fabio Rossi <fabio.rossi@inaf.it>
License: MIT License
Project-URL: repository, https://github.com/astro-tiptop/SYMAO
Requires-Python: >=3.7
License-File: LICENSE
Requires-Dist: numpy
Requires-Dist: scipy
Requires-Dist: sympy
Requires-Dist: astro-seeing>=1.2
Dynamic: license-file
